{"message":{"dataexist":"1","cid":"99743"},"data":{1220832:{"cid":"100827","uid":"1220832","operatorid":"76281","operator":"Lakalaka","action":"禁止发言","reason":"剽窃","dateline":"2015-3-20 21:11","username":"83330066","groupexpiry":"永不过期"},175374:{"cid":"100637","uid":"175374","operatorid":"84901","operator":"pogox","action":"禁止发言","reason":"","dateline":"2015-3-20 16:08","username":"慈悲王子","groupexpiry":"永不过期"},126337:{"cid":"100634","uid":"126337","operatorid":"84901","operator":"pogox","action":"禁止发言","reason":"","dateline":"2015-3-20 16:04","username":"缤纷","groupexpiry":"永不过期"},237703:{"cid":"100427","uid":"237703","operatorid":"240366","operator":"西红柿片","action":"禁止发言","reason":"纯水","dateline":"2015-3-19 22:56","username":"jackiejim","groupexpiry":"永不过期"},881579:{"cid":"100387","uid":"881579","operatorid":"240366","operator":"西红柿片","action":"禁止发言","reason":"剽窃","dateline":"2015-3-19 22:16","username":"mzy737122718","groupexpiry":"永不过期"},681940:{"cid":"100295","uid":"681940","operatorid":"66971","operator":"爱国青年","action":"禁止发言","reason":"刷帖，永久","dateline":"2015-3-19 19:18","username":"sc123560","groupexpiry":"永不过期"},990022:{"cid":"100281","uid":"990022","operatorid":"66971","operator":"爱国青年","action":"禁止发言","reason":"广告机永久封禁","dateline":"2015-3-19 19:01","username":"a1192012668","groupexpiry":"永不过期"},60283:{"cid":"100280","uid":"60283","operatorid":"274490","operator":"SPE__HaiKuo","action":"禁止发言","reason":"刷帖","dateline":"2015-3-19 18:44","username":"lizongjie","groupexpiry":"永不过期"},1238854:{"cid":"100277","uid":"1238854","operatorid":"66971","operator":"爱国青年","action":"禁止发言","reason":"广告机","dateline":"2015-3-19 18:40","username":"zhaoxubin3210","groupexpiry":"永不过期"},483555:{"cid":"99886","uid":"483555","operatorid":"66971","operator":"爱国青年","action":"禁止发言","reason":"签名档恶意文件，永久","dateline":"2015-3-19 15:54","username":"冰之魂魄","groupexpiry":"永不过期"},376567:{"cid":"99881","uid":"376567","operatorid":"42992","operator":"810587921","action":"禁止发言","reason":"后门插件","dateline":"2015-3-19 15:51","username":"刚囊四大","groupexpiry":"永不过期"},264055:{"cid":"99743","uid":"264055","operatorid":"66971","operator":"爱国青年","action":"禁止发言","reason":"广告机","dateline":"2015-3-19 00:53","username":"q1344778945","groupexpiry":"永不过期"}}}