{
  "message": {
    "dataexist": "1",
    "cid": "110938"
  },
  "data": {
    "775292": {
      "cid": "111463",
      "uid": "775292",
      "operatorid": "240366",
      "operator": "西红柿片",
      "action": "禁止发言",
      "reason": "水龙头",
      "dateline": "2015-4-25 21:56",
      "username": "x_lang",
      "groupexpiry": "永不过期"
    },
    "174139": {
      "cid": "111455",
      "uid": "174139",
      "operatorid": "240366",
      "operator": "西红柿片",
      "action": "禁止发言",
      "reason": "水龙头",
      "dateline": "2015-4-25 21:54",
      "username": "smr12138",
      "groupexpiry": "永不过期"
    },
    "758697": {
      "cid": "111454",
      "uid": "758697",
      "operatorid": "240366",
      "operator": "西红柿片",
      "action": "禁止发言",
      "reason": "水龙头",
      "dateline": "2015-4-25 21:52",
      "username": "a2514650997",
      "groupexpiry": "永不过期"
    },
    "622021": {
      "cid": "111444",
      "uid": "622021",
      "operatorid": "66971",
      "operator": "爱国青年",
      "action": "禁止访问",
      "reason": "",
      "dateline": "2015-4-25 21:34",
      "username": "849588414",
      "groupexpiry": "永不过期"
    },
    "1256538": {
      "cid": "111443",
      "uid": "1256538",
      "operatorid": "66971",
      "operator": "爱国青年",
      "action": "禁止发言",
      "reason": "大量无意义灌水刷帖，并利用小号刷分",
      "dateline": "2015-4-25 21:32",
      "username": "流小氓Liu",
      "groupexpiry": "永不过期"
    },
    "1283167": {
      "cid": "111442",
      "uid": "1283167",
      "operatorid": "66971",
      "operator": "爱国青年",
      "action": "禁止发言",
      "reason": "刷分",
      "dateline": "2015-4-25 21:32",
      "username": "流小氓Mang",
      "groupexpiry": "永不过期"
    },
    "1180750": {
      "cid": "111434",
      "uid": "1180750",
      "operatorid": "76964",
      "operator": "zhh0000zhh",
      "action": "禁止发言",
      "reason": "广告机",
      "dateline": "2015-4-25 20:48",
      "username": "wls06a4",
      "groupexpiry": "永不过期"
    },
    "1290627": {
      "cid": "111418",
      "uid": "1290627",
      "operatorid": "3038",
      "operator": "混乱",
      "action": "禁止发言",
      "reason": "",
      "dateline": "2015-4-25 19:13",
      "username": "啊啊爱",
      "groupexpiry": "永不过期"
    },
    "758235": {
      "cid": "111407",
      "uid": "758235",
      "operatorid": "240366",
      "operator": "西红柿片",
      "action": "禁止发言",
      "reason": "别出来了",
      "dateline": "2015-4-25 18:00",
      "username": "121000197",
      "groupexpiry": "永不过期"
    },
    "287481": {
      "cid": "111281",
      "uid": "287481",
      "operatorid": "240366",
      "operator": "西红柿片",
      "action": "禁止发言",
      "reason": "水龙头",
      "dateline": "2015-4-25 10:31",
      "username": "Davidgu",
      "groupexpiry": "永不过期"
    },
    "354841": {
      "cid": "111280",
      "uid": "354841",
      "operatorid": "240366",
      "operator": "西红柿片",
      "action": "禁止发言",
      "reason": "水龙头",
      "dateline": "2015-4-25 10:27",
      "username": "1621233211",
      "groupexpiry": "永不过期"
    },
    "834718": {
      "cid": "111273",
      "uid": "834718",
      "operatorid": "240366",
      "operator": "西红柿片",
      "action": "禁止发言",
      "reason": "水龙头",
      "dateline": "2015-4-25 10:24",
      "username": ".beiweipeng.",
      "groupexpiry": "永不过期"
    },
    "502492": {
      "cid": "111272",
      "uid": "502492",
      "operatorid": "240366",
      "operator": "西红柿片",
      "action": "禁止发言",
      "reason": "水龙头",
      "dateline": "2015-4-25 10:19",
      "username": "无语114",
      "groupexpiry": "永不过期"
    },
    "1038285": {
      "cid": "111244",
      "uid": "1038285",
      "operatorid": "240366",
      "operator": "西红柿片",
      "action": "禁止发言",
      "reason": "水龙头",
      "dateline": "2015-4-25 10:08",
      "username": "dazzle_M",
      "groupexpiry": "永不过期"
    },
    "183617": {
      "cid": "111242",
      "uid": "183617",
      "operatorid": "240366",
      "operator": "西红柿片",
      "action": "禁止发言",
      "reason": "水龙头",
      "dateline": "2015-4-25 10:06",
      "username": "温彦荣",
      "groupexpiry": "永不过期"
    },
    "1186219": {
      "cid": "111236",
      "uid": "1186219",
      "operatorid": "240366",
      "operator": "西红柿片",
      "action": "禁止发言",
      "reason": "水龙头",
      "dateline": "2015-4-25 10:04",
      "username": "swz198",
      "groupexpiry": "永不过期"
    },
    "169023": {
      "cid": "111235",
      "uid": "169023",
      "operatorid": "240366",
      "operator": "西红柿片",
      "action": "禁止发言",
      "reason": "水龙头",
      "dateline": "2015-4-25 10:02",
      "username": "20030313",
      "groupexpiry": "永不过期"
    },
    "1080935": {
      "cid": "111225",
      "uid": "1080935",
      "operatorid": "240366",
      "operator": "西红柿片",
      "action": "禁止发言",
      "reason": "水龙头",
      "dateline": "2015-4-25 09:59",
      "username": "@~Minecraft~@",
      "groupexpiry": "永不过期"
    },
    "1060598": {
      "cid": "111215",
      "uid": "1060598",
      "operatorid": "240366",
      "operator": "西红柿片",
      "action": "禁止发言",
      "reason": "水龙头",
      "dateline": "2015-4-25 09:59",
      "username": "2453260321",
      "groupexpiry": "永不过期"
    },
    "498505": {
      "cid": "111214",
      "uid": "498505",
      "operatorid": "240366",
      "operator": "西红柿片",
      "action": "禁止发言",
      "reason": "水龙头",
      "dateline": "2015-4-25 09:56",
      "username": "maoyitian88",
      "groupexpiry": "永不过期"
    },
    "990723": {
      "cid": "111192",
      "uid": "990723",
      "operatorid": "240366",
      "operator": "西红柿片",
      "action": "禁止发言",
      "reason": "水龙头",
      "dateline": "2015-4-25 09:49",
      "username": "liuhanson",
      "groupexpiry": "永不过期"
    },
    "458830": {
      "cid": "111191",
      "uid": "458830",
      "operatorid": "240366",
      "operator": "西红柿片",
      "action": "禁止发言",
      "reason": "水龙头",
      "dateline": "2015-4-25 09:48",
      "username": "673734169",
      "groupexpiry": "永不过期"
    },
    "1094092": {
      "cid": "111073",
      "uid": "1094092",
      "operatorid": "293851",
      "operator": "小白勇者",
      "action": "禁止发言",
      "reason": "刷帖。",
      "dateline": "2015-4-25 00:51",
      "username": "20050131erzi",
      "groupexpiry": "永不过期"
    },
    "1130354": {
      "cid": "110940",
      "uid": "1130354",
      "operatorid": "240366",
      "operator": "西红柿片",
      "action": "禁止发言",
      "reason": "水龙头",
      "dateline": "2015-4-24 23:34",
      "username": "sasaki_haise",
      "groupexpiry": "永不过期"
    },
    "1238075": {
      "cid": "110938",
      "uid": "1238075",
      "operatorid": "1009269",
      "operator": "PETER·篠",
      "action": "禁止发言",
      "reason": "严重刷帖。",
      "dateline": "2015-4-24 23:32",
      "username": "绍珉",
      "groupexpiry": "永不过期"
    }
  }
}