{
  "message": {
    "dataexist": "1",
    "cid": "613612"
  },
  "data": {
    "2560586": {
      "cid": "616523",
      "uid": "2560586",
      "operatorid": "5367",
      "operator": "john180",
      "action": "禁止发言",
      "reason": "水龙头",
      "dateline": "\u003cspan title\u003d\"2020-4-26 22:56\"\u003e前天\u0026nbsp;22:56\u003c/span\u003e",
      "username": "玲玲小姐姐",
      "groupexpiry": "2020-5-1 22:56"
    },
    "3210828": {
      "cid": "616522",
      "uid": "3210828",
      "operatorid": "5367",
      "operator": "john180",
      "action": "禁止发言",
      "reason": "水龙头",
      "dateline": "\u003cspan title\u003d\"2020-4-26 22:55\"\u003e前天\u0026nbsp;22:55\u003c/span\u003e",
      "username": "wogiao666",
      "groupexpiry": "2020-5-1 22:55"
    },
    "1643300": {
      "cid": "616521",
      "uid": "1643300",
      "operatorid": "5367",
      "operator": "john180",
      "action": "禁止发言",
      "reason": "水龙头",
      "dateline": "\u003cspan title\u003d\"2020-4-26 22:54\"\u003e前天\u0026nbsp;22:54\u003c/span\u003e",
      "username": "幻灭c",
      "groupexpiry": "2020-5-3 22:54"
    },
    "1234113": {
      "cid": "616519",
      "uid": "1234113",
      "operatorid": "5367",
      "operator": "john180",
      "action": "禁止发言",
      "reason": "水龙头",
      "dateline": "\u003cspan title\u003d\"2020-4-26 22:53\"\u003e前天\u0026nbsp;22:53\u003c/span\u003e",
      "username": "初情",
      "groupexpiry": "2020-5-1 22:53"
    },
    "1832818": {
      "cid": "616518",
      "uid": "1832818",
      "operatorid": "5367",
      "operator": "john180",
      "action": "禁止发言",
      "reason": "水龙头",
      "dateline": "\u003cspan title\u003d\"2020-4-26 22:52\"\u003e前天\u0026nbsp;22:52\u003c/span\u003e",
      "username": "薄荷神",
      "groupexpiry": "2020-5-1 22:52"
    },
    "2113322": {
      "cid": "616517",
      "uid": "2113322",
      "operatorid": "5367",
      "operator": "john180",
      "action": "禁止发言",
      "reason": "水龙头",
      "dateline": "\u003cspan title\u003d\"2020-4-26 22:52\"\u003e前天\u0026nbsp;22:52\u003c/span\u003e",
      "username": "1846924185",
      "groupexpiry": "2020-5-1 22:52"
    },
    "2846965": {
      "cid": "616408",
      "uid": "2846965",
      "operatorid": "108341",
      "operator": "U1U420039",
      "action": "禁止发言",
      "reason": "水龙头",
      "dateline": "\u003cspan title\u003d\"2020-4-26 20:08\"\u003e前天\u0026nbsp;20:08\u003c/span\u003e",
      "username": "3493086769",
      "groupexpiry": "永不过期"
    },
    "3126473": {
      "cid": "616194",
      "uid": "3126473",
      "operatorid": "790748",
      "operator": "酉月一",
      "action": "禁止发言",
      "reason": "剽窃",
      "dateline": "\u003cspan title\u003d\"2020-4-26 18:39\"\u003e前天\u0026nbsp;18:39\u003c/span\u003e",
      "username": "细致A",
      "groupexpiry": "2020-5-10 18:39"
    },
    "2775408": {
      "cid": "615679",
      "uid": "2775408",
      "operatorid": "5367",
      "operator": "john180",
      "action": "禁止发言",
      "reason": "超长评分",
      "dateline": "\u003cspan title\u003d\"2020-4-26 13:52\"\u003e前天\u0026nbsp;13:52\u003c/span\u003e",
      "username": "huzpsb",
      "groupexpiry": "2020-5-3 13:52"
    },
    "1748995": {
      "cid": "615535",
      "uid": "1748995",
      "operatorid": "5367",
      "operator": "john180",
      "action": "禁止发言",
      "reason": "签名档多次违规",
      "dateline": "\u003cspan title\u003d\"2020-4-26 10:04\"\u003e前天\u0026nbsp;10:04\u003c/span\u003e",
      "username": "Brave_boy",
      "groupexpiry": "2020-5-1 10:04"
    },
    "2828505": {
      "cid": "615482",
      "uid": "2828505",
      "operatorid": "5367",
      "operator": "john180",
      "action": "禁止发言",
      "reason": "超长评分,自首从轻处罚",
      "dateline": "\u003cspan title\u003d\"2020-4-25 23:32\"\u003e3\u0026nbsp;天前\u003c/span\u003e",
      "username": "专刀你",
      "groupexpiry": "2020-4-28 23:32"
    },
    "615092": {
      "cid": "615481",
      "uid": "615092",
      "operatorid": "5367",
      "operator": "john180",
      "action": "禁止发言",
      "reason": "违反版规2-4-D",
      "dateline": "\u003cspan title\u003d\"2020-4-25 23:29\"\u003e3\u0026nbsp;天前\u003c/span\u003e",
      "username": "Una",
      "groupexpiry": "2020-4-28 23:29"
    },
    "2656657": {
      "cid": "615478",
      "uid": "2656657",
      "operatorid": "5367",
      "operator": "john180",
      "action": "禁止发言",
      "reason": "超长评分",
      "dateline": "\u003cspan title\u003d\"2020-4-25 23:17\"\u003e3\u0026nbsp;天前\u003c/span\u003e",
      "username": "MEMZJJY",
      "groupexpiry": "2020-5-2 23:17"
    },
    "3155131": {
      "cid": "615079",
      "uid": "3155131",
      "operatorid": "46925",
      "operator": "xukarhei",
      "action": "禁止发言",
      "reason": "水龙头",
      "dateline": "\u003cspan title\u003d\"2020-4-25 20:24\"\u003e3\u0026nbsp;天前\u003c/span\u003e",
      "username": "桐谷和人.1",
      "groupexpiry": "2020-6-24 20:24"
    },
    "2465164": {
      "cid": "614973",
      "uid": "2465164",
      "operatorid": "2067786",
      "operator": "消",
      "action": "禁止发言",
      "reason": "违规商业神奇宝贝服",
      "dateline": "\u003cspan title\u003d\"2020-4-25 17:37\"\u003e3\u0026nbsp;天前\u003c/span\u003e",
      "username": "QSZQSZ00",
      "groupexpiry": "2020-5-25 17:37"
    },
    "571937": {
      "cid": "614858",
      "uid": "571937",
      "operatorid": "2006215",
      "operator": "skyliye",
      "action": "禁止发言",
      "reason": "水龙头",
      "dateline": "\u003cspan title\u003d\"2020-4-25 15:12\"\u003e3\u0026nbsp;天前\u003c/span\u003e",
      "username": "lihaoming",
      "groupexpiry": "2020-5-9 15:12"
    },
    "1607523": {
      "cid": "614659",
      "uid": "1607523",
      "operatorid": "86237",
      "operator": "缇米Official",
      "action": "禁止发言",
      "reason": "2-4-D 恶性挑起事端",
      "dateline": "\u003cspan title\u003d\"2020-4-25 14:29\"\u003e3\u0026nbsp;天前\u003c/span\u003e",
      "username": "爱情不是爱",
      "groupexpiry": "2020-5-2 14:29"
    },
    "2517438": {
      "cid": "614576",
      "uid": "2517438",
      "operatorid": "2511498",
      "operator": "AzureHanChen",
      "action": "禁止发言",
      "reason": "服务端版块 版规2-6-4 宣传盈利性广告",
      "dateline": "\u003cspan title\u003d\"2020-4-25 14:05\"\u003e3\u0026nbsp;天前\u003c/span\u003e",
      "username": "这个过去",
      "groupexpiry": "2020-5-2 14:05"
    },
    "2682678": {
      "cid": "614441",
      "uid": "2682678",
      "operatorid": "2511498",
      "operator": "AzureHanChen",
      "action": "禁止发言",
      "reason": "服务端版块 版规2-6-4 情节严重",
      "dateline": "\u003cspan title\u003d\"2020-4-25 10:52\"\u003e3\u0026nbsp;天前\u003c/span\u003e",
      "username": "3193125015",
      "groupexpiry": "永不过期"
    },
    "3246519": {
      "cid": "614322",
      "uid": "3246519",
      "operatorid": "2511498",
      "operator": "AzureHanChen",
      "action": "禁止发言",
      "reason": "水龙头",
      "dateline": "\u003cspan title\u003d\"2020-4-25 10:29\"\u003e3\u0026nbsp;天前\u003c/span\u003e",
      "username": "757337822",
      "groupexpiry": "永不过期"
    },
    "2952954": {
      "cid": "614321",
      "uid": "2952954",
      "operatorid": "2511498",
      "operator": "AzureHanChen",
      "action": "禁止发言",
      "reason": "剽窃",
      "dateline": "\u003cspan title\u003d\"2020-4-25 10:26\"\u003e3\u0026nbsp;天前\u003c/span\u003e",
      "username": "Enrol_laomeng",
      "groupexpiry": "2020-5-9 10:26"
    },
    "2717791": {
      "cid": "613966",
      "uid": "2717791",
      "operatorid": "790748",
      "operator": "酉月一",
      "action": "禁止发言",
      "reason": "水龙头",
      "dateline": "\u003cspan title\u003d\"2020-4-25 06:15\"\u003e3\u0026nbsp;天前\u003c/span\u003e",
      "username": "159426837",
      "groupexpiry": "2020-5-2 06:15"
    },
    "2789931": {
      "cid": "613633",
      "uid": "2789931",
      "operatorid": "5367",
      "operator": "john180",
      "action": "禁止发言",
      "reason": "水龙头",
      "dateline": "\u003cspan title\u003d\"2020-4-24 23:50\"\u003e4\u0026nbsp;天前\u003c/span\u003e",
      "username": "wang10009",
      "groupexpiry": "2020-5-1 23:50"
    },
    "2669495": {
      "cid": "613632",
      "uid": "2669495",
      "operatorid": "5367",
      "operator": "john180",
      "action": "禁止发言",
      "reason": "水龙头",
      "dateline": "\u003cspan title\u003d\"2020-4-24 23:49\"\u003e4\u0026nbsp;天前\u003c/span\u003e",
      "username": "2582689271",
      "groupexpiry": "2020-4-29 23:49"
    },
    "1485144": {
      "cid": "613622",
      "uid": "1485144",
      "operatorid": "5367",
      "operator": "john180",
      "action": "禁止发言",
      "reason": "水龙头",
      "dateline": "\u003cspan title\u003d\"2020-4-24 23:43\"\u003e4\u0026nbsp;天前\u003c/span\u003e",
      "username": "kitchenmm",
      "groupexpiry": "2020-4-29 23:43"
    },
    "2478373": {
      "cid": "613617",
      "uid": "2478373",
      "operatorid": "5367",
      "operator": "john180",
      "action": "禁止发言",
      "reason": "水龙头",
      "dateline": "\u003cspan title\u003d\"2020-4-24 23:42\"\u003e4\u0026nbsp;天前\u003c/span\u003e",
      "username": "2656989851",
      "groupexpiry": "2020-4-29 23:42"
    },
    "2501791": {
      "cid": "613615",
      "uid": "2501791",
      "operatorid": "5367",
      "operator": "john180",
      "action": "禁止发言",
      "reason": "水龙头",
      "dateline": "\u003cspan title\u003d\"2020-4-24 23:42\"\u003e4\u0026nbsp;天前\u003c/span\u003e",
      "username": "t481382257",
      "groupexpiry": "2020-4-29 23:42"
    },
    "226969": {
      "cid": "613612",
      "uid": "226969",
      "operatorid": "5367",
      "operator": "john180",
      "action": "禁止发言",
      "reason": "水龙头",
      "dateline": "\u003cspan title\u003d\"2020-4-24 23:42\"\u003e4\u0026nbsp;天前\u003c/span\u003e",
      "username": "めぐみん",
      "groupexpiry": "2020-4-29 23:42"
    }
  }
}